Metadata-Version: 2.1
Name: django-payfast-4
Version: 0.1.1
Summary: A pluggable Django application for integrating payfast.co.za payment system.
Home-page: https://github.com/pjdelport/django-payfast
Maintainer: Ruan Steenkamp
Maintainer-email: ruanesteenkamp@gmail.com
License: MIT license
Classifier: Development Status :: 3 - Alpha
Classifier: Environment :: Web Environment
Classifier: Framework :: Django
Classifier: Intended Audience :: Developers
Classifier: License :: OSI Approved :: MIT License
Classifier: Programming Language :: Python :: 3
Classifier: Topic :: Software Development :: Libraries :: Python Modules
License-File: LICENSE.txt
Requires-Dist: six
Requires-Dist: Django
Requires-Dist: typing ; python_version < "3.5"
